octodns_namedfileyaml/__init__.py
octodns_namedfileyaml-0.0.2.dist-info/LICENSE
octodns_namedfileyaml-0.0.2.dist-info/METADATA
octodns_namedfileyaml-0.0.2.dist-info/WHEEL
octodns_namedfileyaml-0.0.2.dist-info/top_level.txt
octodns_namedfileyaml-0.0.2.dist-info/RECORD
