Metadata-Version: 2.1
Name: octodns-namedfileyaml
Version: 0.0.2
Summary: A named YAML file provider for octoDNS
Home-page: https://github.com/felixoi/octodns-namedfileyaml
Author: felixoi
Author-email: dev@felixoi.com
License: MIT
Requires-Python: >=3.6
License-File: LICENSE
Requires-Dist: octodns (>=0.9.21)
Provides-Extra: dev
Requires-Dist: pytest ; extra == 'dev'
Requires-Dist: pytest-cov ; extra == 'dev'
Requires-Dist: pytest-network ; extra == 'dev'
Requires-Dist: black (>=22.3.0) ; extra == 'dev'
Requires-Dist: build (>=0.7.0) ; extra == 'dev'
Requires-Dist: pyflakes (>=2.2.0) ; extra == 'dev'
Requires-Dist: readme-renderer[md] (>=26.0) ; extra == 'dev'
Requires-Dist: twine (>=3.4.2) ; extra == 'dev'
Provides-Extra: test
Requires-Dist: pytest ; extra == 'test'
Requires-Dist: pytest-cov ; extra == 'test'
Requires-Dist: pytest-network ; extra == 'test'
